crossfit/__init__.py
crossfit/_version.py
crossfit/py.typed
crossfit/backend/__init__.py
crossfit/backend/gpu.py
crossfit/backend/cudf/__init__.py
crossfit/backend/cudf/array.py
crossfit/backend/cudf/dataframe.py
crossfit/backend/cudf/series.py
crossfit/backend/cupy/__init__.py
crossfit/backend/cupy/array.py
crossfit/backend/cupy/kernels.py
crossfit/backend/cupy/sparse.py
crossfit/backend/dask/__init__.py
crossfit/backend/dask/aggregate.py
crossfit/backend/dask/cluster.py
crossfit/backend/dask/dataframe.py
crossfit/backend/numpy/__init__.py
crossfit/backend/numpy/sparse.py
crossfit/backend/pandas/__init__.py
crossfit/backend/pandas/array.py
crossfit/backend/pandas/dataframe.py
crossfit/backend/torch/__init__.py
crossfit/backend/torch/array.py
crossfit/backend/torch/loader.py
crossfit/backend/torch/model.py
crossfit/backend/torch/hf/__init__.py
crossfit/backend/torch/hf/memory_curve_utils.py
crossfit/backend/torch/hf/model.py
crossfit/backend/torch/op/__init__.py
crossfit/backend/torch/op/base.py
crossfit/backend/torch/op/embed.py
crossfit/backend/torch/op/vector_search.py
crossfit/calculate/__init__.py
crossfit/calculate/aggregate.py
crossfit/calculate/calculate.py
crossfit/calculate/frame.py
crossfit/calculate/module.py
crossfit/data/__init__.py
crossfit/data/array/__init__.py
crossfit/data/array/conversion.py
crossfit/data/array/decorator.py
crossfit/data/array/dispatch.py
crossfit/data/array/masked.py
crossfit/data/array/ops.py
crossfit/data/dataframe/__init__.py
crossfit/data/dataframe/core.py
crossfit/data/dataframe/dispatch.py
crossfit/data/sparse/__init__.py
crossfit/data/sparse/core.py
crossfit/data/sparse/dispatch.py
crossfit/data/sparse/ranking.py
crossfit/dataset/__init__.py
crossfit/dataset/base.py
crossfit/dataset/home.py
crossfit/dataset/load.py
crossfit/dataset/beir/__init__.py
crossfit/dataset/beir/load.py
crossfit/dataset/beir/raw.py
crossfit/metric/__init__.py
crossfit/metric/base.py
crossfit/metric/common.py
crossfit-0.0.9.dist-info/licenses/LICENSE
crossfit-0.0.9.dist-info/METADATA
crossfit-0.0.9.dist-info/WHEEL
crossfit-0.0.9.dist-info/top_level.txt
crossfit-0.0.9.dist-info/RECORD
